jestimator/__init__.py
jestimator/amos.py
jestimator/amos_helper.py
jestimator-0.3.3.dist-info/LICENSE
jestimator-0.3.3.dist-info/WHEEL
jestimator-0.3.3.dist-info/METADATA
jestimator-0.3.3.dist-info/RECORD
