Metadata-Version: 2.1
Name: jestimator
Version: 0.3.3
Summary: Implementation of the Amos optimizer from the JEstimator lib.
Keywords: 
Author-email: jestimator authors <no-reply@google.com>
Requires-Python: >=3.7
Classifier: Programming Language :: Python :: 3
Classifier: Programming Language :: Python :: 3 :: Only
Classifier: License :: OSI Approved :: Apache Software License
Classifier: Intended Audience :: Science/Research
Requires-Dist: flax
Requires-Dist: absl-py ; extra == "test"
Project-URL: homepage, https://github.com/google-research/jestimator
Project-URL: repository, https://github.com/google-research/jestimator
Provides-Extra: test
